{
  "projectId": "3391305001861538506",
  "requestedId": "88ebc935472544f5ae5828a887efcbca",
  "title": "漫画源文本导入弹窗",
  "stitchTitle": "漫画源文本导入弹窗",
  "resourceName": "projects/3391305001861538506/screens/88ebc935472544f5ae5828a887efcbca",
  "deviceType": "MOBILE",
  "width": "780",
  "height": "1768",
  "files": {
    "screenshot": {
      "path": "stitch-export/screens/63-漫画源文本导入弹窗/screenshot.png",
      "mimeType": "image/png",
      "bytes": 117982,
      "resourceName": "projects/3391305001861538506/files/116ef63cde574043acacdefc63e3e339"
    },
    "code": {
      "path": "stitch-export/screens/63-漫画源文本导入弹窗/code.html",
      "mimeType": "text/html",
      "bytes": 9395,
      "resourceName": "projects/3391305001861538506/files/aa58545f12364ee28e93e9fb3cebd7bd"
    }
  }
}
